wallpaper/__init__.py
wallpaper/main.py
wallpaper/wallpaper.py
BingWallpaper-1.2.2.dist-info/METADATA
BingWallpaper-1.2.2.dist-info/WHEEL
BingWallpaper-1.2.2.dist-info/entry_points.txt
BingWallpaper-1.2.2.dist-info/top_level.txt
BingWallpaper-1.2.2.dist-info/RECORD
