Metadata-Version: 2.1
Name: BingWallpaper
Version: 1.2.2
Summary: A python script which can download bing's beautiful images and set the image to your computer wallpaper.
Home-page: https://github.com/LogicJake/some-scripts/tree/master/bing-wallpaper
Author: LogicJake
Author-email: chenyangshi1996@gamil.com
License: MIT
Platform: UNKNOWN
Requires-Dist: requests
